persian_datetime/__init__.py
persian_datetime/datetime.py
persian_datetime-0.10.3.dist-info/LICENSE
persian_datetime-0.10.3.dist-info/METADATA
persian_datetime-0.10.3.dist-info/WHEEL
persian_datetime-0.10.3.dist-info/top_level.txt
persian_datetime-0.10.3.dist-info/RECORD
