Metadata-Version: 2.1
Name: persian-datetime
Version: 0.10.3
Summary: Persian (jalali) datetime کلاس کار با تاریخ فارسی
Home-page: https://github.com/alishekari/python-persian-datetime
Author: Ali Shekari
Author-email: alishekari1991@outlook.com
Classifier: Programming Language :: Python :: 3.9
Classifier: License :: OSI Approved :: MIT License
Classifier: Operating System :: OS Independent
Requires-Python: >=3.0
License-File: LICENSE
Requires-Dist: djangorestframework
